README.rst
setup.py
jinja_vanish/__init__.py
jinja_vanish.egg-info/PKG-INFO
jinja_vanish.egg-info/SOURCES.txt
jinja_vanish.egg-info/dependency_links.txt
jinja_vanish.egg-info/requires.txt
jinja_vanish.egg-info/top_level.txt