Metadata-Version: 1.1
Name: jinja-vanish
Version: 0.1
Summary: Customizable auto-escaping for jinja2.
Home-page: https://github.com/mbr/jinja-vanish
Author: Marc Brinkmann
Author-email: git@marcbrinkmann.de
License: MIT
Platform: UNKNOWN
Classifier: Programming Language :: Python :: 2
Classifier: Programming Language :: Python :: 3
